wei_dev/__init__.py
wei_dev/__main__.py
wei_dev/constants.py
wei_dev/gui.py
wei_dev/sample_msg.py
wei_dev/sender.py
wei_dev/templates.py
wei_dev-0.2.0.dist-info/DESCRIPTION.rst
wei_dev-0.2.0.dist-info/METADATA
wei_dev-0.2.0.dist-info/RECORD
wei_dev-0.2.0.dist-info/WHEEL
wei_dev-0.2.0.dist-info/metadata.json
wei_dev-0.2.0.dist-info/top_level.txt
