Metadata-Version: 2.0
Name: wei-dev
Version: 0.2.0
Summary: DevTool for weichat development and testing, GUI and CLI tool and testing util-library included.
Home-page: UNKNOWN
Author: UNKNOWN
Author-email: UNKNOWN
License: UNKNOWN
Platform: UNKNOWN
Requires-Dist: cmdtree
Requires-Dist: requests
